boxexporter
