Metadata-Version: 1.0
Name: box-exporter
Version: 0.0.2
Summary: A utility that allows you to export data from a database to a folder on box
Home-page: UNKNOWN
Author: m1yag1
Author-email: me@mikefromit.com
License: AGPLv3
Platform: UNKNOWN
